unalix/__init__.py
unalix/__version__.py
unalix/config/__init__.py
unalix/config/http.py
unalix/config/paths.py
unalix/config/rulesets.py
unalix/core/__init__.py
unalix/core/cookie_policies.py
unalix/core/coreutils.py
unalix/core/ssl_context.py
unalix/core/url_cleaner.py
unalix/core/url_unshort.py
unalix/exceptions/__init__.py
unalix/exceptions/http.py
unalix/package_data/ca/ca-bundle.crt
unalix/package_data/other/redirects_from_body.json
unalix/package_data/policies/cookies_allow.json
unalix/package_data/rulesets/data.min.json
unalix/package_data/rulesets/unalix.json
unalix/types/__init__.py
unalix/types/body_redirects.py
unalix/types/domains.py
unalix/types/objects.py
unalix/types/patterns.py
unalix/types/responses.py
unalix/types/rulesets.py
unalix/types/urls.py
unalix/utils/__init__.py
unalix/utils/http.py
unalix_rev-0.9.1.dist-info/METADATA
unalix_rev-0.9.1.dist-info/WHEEL
unalix_rev-0.9.1.dist-info/licenses/LICENSE
unalix_rev-0.9.1.dist-info/RECORD
