Metadata-Version: 2.1
Name: Unalix-Rev
Version: 0.9.1
Summary: Small, dependency-free, fast Python package for removing tracking fields from URLs.
Author-Email: SnwMds <snwmds@tutanota.com>
Maintainer-Email: icealtria <icealtria@gmail.com>
License: LGPL-3.0
Classifier: Development Status :: 5 - Production/Stable
Classifier: Intended Audience :: Developers
Classifier: License :: OSI Approved :: GNU Lesser General Public License v3 (LGPLv3)
Classifier: Operating System :: Android
Classifier: Operating System :: MacOS
Classifier: Operating System :: Microsoft :: Windows
Classifier: Operating System :: Unix
Classifier: Programming Language :: Python :: 3.10
Classifier: Programming Language :: Python :: 3.11
Classifier: Programming Language :: Python :: 3.7
Classifier: Programming Language :: Python :: 3.8
Classifier: Programming Language :: Python :: 3.9
Classifier: Programming Language :: Python :: Implementation :: PyPy
Classifier: Topic :: Internet
Classifier: Topic :: Security
Project-URL: Homepage, https://github.com/icealtria/Unalix-Rev
Project-URL: Bug tracker, https://github.com/icealtria/Unalix-Rev/issues
Requires-Python: >=3.7
